wininput/__init__.py
wininput/common.py
wininput/keyboard.py
pywin_input-0.0.2.dist-info/LICENSE
pywin_input-0.0.2.dist-info/METADATA
pywin_input-0.0.2.dist-info/WHEEL
pywin_input-0.0.2.dist-info/top_level.txt
pywin_input-0.0.2.dist-info/RECORD
