Metadata-Version: 2.1
Name: pywin-input
Version: 0.0.2
Summary: A lightweight library to simulate keyboard and mouse input
Home-page: https://github.com/avble/keyboardNG
Author: Avble Harry
Author-email: avble.harry@gmail.com
License: UNKNOWN
Project-URL: Bug Tracker, https://github.com/avble/keyboardNG/issues
Platform: UNKNOWN
Classifier: Programming Language :: Python :: 3
Classifier: License :: OSI Approved :: MIT License
Classifier: Operating System :: OS Independent
Requires-Python: >=3.6
License-File: LICENSE
